[
  {
    "Language": "http://www.wikidata.org/entity/Q7277404",
    "Properties": [
      {
        "Property": "http://schema.org/version",
        "Values": [
          "1729780858"
        ]
      },
      {
        "Property": "http://schema.org/dateModified",
        "Values": [
          "2022-09-16T11:00:06Z"
        ]
      },
      {
        "Property": "http://schema.org/description",
        "Values": [
          "j\u0119zyk programowania",
          "linguagem de programa\u00e7\u00e3o",
          "programmeringssprog",
          "programovac\u00ed jazyk",
          "programspr\u00e5k",
          "linguaggio di programmazione",
          "llenguatge de programaci\u00f3",
          "yezh programmi\u00f1",
          "\u092a\u094d\u0930\u094b\u0917\u094d\u0930\u093e\u092e\u093f\u0902\u0917 \u092d\u093e\u0937\u093e",
          "programmeringsspr\u00e5k",
          "limbaj de programare",
          "Programmiersprache",
          "\u0a2a\u0a4d\u0a30\u0a4b\u0a17\u0a30\u0a3e\u0a2e\u0a3f\u0a70\u0a17 \u0a2d\u0a3e\u0a38\u0a3c\u0a3e",
          "lenguaje de programaci\u00f3n",
          "ohjelmointikieli",
          "langage de programmation",
          "\u05e9\u05e4\u05ea \u05ea\u05db\u05e0\u05d5\u05ea",
          "programmeertaal",
          "multiparadigm programming language targeted at AI applications",
          "\u0d2a\u0d4d\u0d30\u0d4b\u0d17\u0d4d\u0d30\u0d3e\u0d2e\u0d3f\u0d19\u0d4d \u0d2d\u0d3e\u0d37"
        ]
      },
      {
        "Property": "http://www.w3.org/2000/01/rdf-schema#label",
        "Values": [
          "ROOP"
        ]
      },
      {
        "Property": "http://wikiba.se/ontology#statements",
        "Values": [
          "7"
        ]
      },
      {
        "Property": "http://wikiba.se/ontology#sitelinks",
        "Values": [
          "1"
        ]
      },
      {
        "Property": "http://wikiba.se/ontology#identifiers",
        "Values": [
          "2"
        ]
      },
      {
        "Property": "http://www.wikidata.org/prop/direct/instance of",
        "Values": [
          "http://www.wikidata.org/entity/Q9143"
        ]
      },
      {
        "Property": "http://www.wikidata.org/prop/instance of",
        "Values": [
          "http://www.wikidata.org/entity/statement/q7277404-CB423095-2481-452D-9158-8F56AF4277AE"
        ]
      },
      {
        "Property": "http://www.wikidata.org/prop/direct/inception",
        "Values": [
          "1995-01-01T00:00:00Z"
        ]
      },
      {
        "Property": "http://www.wikidata.org/prop/direct/Freebase ID",
        "Values": [
          "/m/03r370"
        ]
      },
      {
        "Property": "http://www.wikidata.org/prop/direct/programming paradigm",
        "Values": [
          "http://www.wikidata.org/entity/Q79872",
          "http://www.wikidata.org/entity/Q1418502",
          "http://www.wikidata.org/entity/Q275603"
        ]
      },
      {
        "Property": "http://www.wikidata.org/prop/direct/Microsoft Academic ID",
        "Values": [
          "2781072724"
        ]
      },
      {
        "Property": "http://www.wikidata.org/prop/direct-normalized/Freebase ID",
        "Values": [
          "http://g.co/kg/m/03r370"
        ]
      },
      {
        "Property": "http://www.wikidata.org/prop/direct-normalized/Microsoft Academic ID",
        "Values": [
          "http://ma-graph.org/entity/2781072724"
        ]
      },
      {
        "Property": "http://www.wikidata.org/prop/inception",
        "Values": [
          "http://www.wikidata.org/entity/statement/Q7277404-8bdd1f03-4d80-f94b-125e-ce8a1e0a7488"
        ]
      },
      {
        "Property": "http://www.wikidata.org/prop/Freebase ID",
        "Values": [
          "http://www.wikidata.org/entity/statement/Q7277404-89A5439B-B48E-482B-A4A4-CF2FB0BCF353"
        ]
      },
      {
        "Property": "http://www.wikidata.org/prop/programming paradigm",
        "Values": [
          "http://www.wikidata.org/entity/statement/Q7277404-57f70fb1-49e1-1f8a-0b70-2ccbc73706ee",
          "http://www.wikidata.org/entity/statement/Q7277404-0f6b8f15-4991-79bb-d66e-83fdcbb102cd",
          "http://www.wikidata.org/entity/statement/Q7277404-855d44c4-48e5-a8bd-8910-82656007db82"
        ]
      },
      {
        "Property": "http://www.wikidata.org/prop/Microsoft Academic ID",
        "Values": [
          "http://www.wikidata.org/entity/statement/Q7277404-679844FD-A094-441B-8F0F-95B42AE45720"
        ]
      }
    ]
  }
]